lazy_schema/__init__.py
lazy_schema/field.py
lazy_schema/schema.py
lazy_schema/schema_pool.py
lazy_schema/utils.py
lazy_schema/value_setter.py
lazy_schema-0.4.0.dist-info/METADATA
lazy_schema-0.4.0.dist-info/WHEEL
lazy_schema-0.4.0.dist-info/RECORD
