Metadata-Version: 2.1
Name: lazy-schema
Version: 0.4.0
Summary: 
Author: MisterNyan
Author-email: michael.edmund.wong@gmail.com
Requires-Python: >=3.8,<4.0
Classifier: Programming Language :: Python :: 3
Classifier: Programming Language :: Python :: 3.8
Classifier: Programming Language :: Python :: 3.9
Classifier: Programming Language :: Python :: 3.10
Classifier: Programming Language :: Python :: 3.11
Classifier: Programming Language :: Python :: 3.12
